{"totalCoins":24,"z_length":7.0,"data":[{"name":"Container","pos":{"x":-4.0,"y":3.799999952316284,"z":0.0},"rot":{"x":0.0,"y":0.0,"z":0.0},"fullRotationData":[],"timelineAnimation":[{"timeLineData":[{"move":true,"rotate":false,"duration":1.0,"data":{"x":4.0,"y":0.0,"z":0.0},"easeType":1},{"move":true,"rotate":false,"duration":1.0,"data":{"x":0.0,"y":0.0,"z":0.0},"easeType":1}]}],"bossSettings":[],"moveForward":[],"soData":[],"mat":[],"isChild":false},{"name":"palm","pos":{"x":-14.460000038146973,"y":-0.25999999046325686,"z":0.0},"rot":{"x":0.0,"y":0.0,"z":0.0},"fullRotationData":[],"timelineAnimation":[],"bossSettings":[],"moveForward":[],"soData":[{"size":{"x":0.0,"y":0.0,"z":0.0},"bumperForce":0.0,"random_pos_x":2.0,"minPayers":0}],"mat":[],"isChild":true},{"name":"Coin","pos":{"x":-4.960000038146973,"y":1.5,"z":-0.11999999731779099},"rot":{"x":0.0,"y":0.0,"z":0.0},"fullRotationData":[],"timelineAnimation":[],"bossSettings":[],"moveForward":[],"soData":[],"mat":[],"isChild":true},{"name":"Coin","pos":{"x":-3.359999895095825,"y":1.5,"z":-0.11999999731779099},"rot":{"x":0.0,"y":0.0,"z":0.0},"fullRotationData":[],"timelineAnimation":[],"bossSettings":[],"moveForward":[],"soData":[],"mat":[],"isChild":true},{"name":"Coin","pos":{"x":-4.159999847412109,"y":1.5,"z":1.4800000190734864},"rot":{"x":0.0,"y":0.0,"z":0.0},"fullRotationData":[],"timelineAnimation":[],"bossSettings":[],"moveForward":[],"soData":[],"mat":[],"isChild":true},{"name":"Coin","pos":{"x":-2.559999942779541,"y":1.5,"z":1.4800000190734864},"rot":{"x":0.0,"y":0.0,"z":0.0},"fullRotationData":[],"timelineAnimation":[],"bossSettings":[],"moveForward":[],"soData":[],"mat":[],"isChild":true},{"name":"Coin","pos":{"x":-5.760000228881836,"y":1.5,"z":1.4800000190734864},"rot":{"x":0.0,"y":0.0,"z":0.0},"fullRotationData":[],"timelineAnimation":[],"bossSettings":[],"moveForward":[],"soData":[],"mat":[],"isChild":true},{"name":"Coin","pos":{"x":-4.159999847412109,"y":1.5,"z":-1.7200000286102296},"rot":{"x":0.0,"y":0.0,"z":0.0},"fullRotationData":[],"timelineAnimation":[],"bossSettings":[],"moveForward":[],"soData":[],"mat":[],"isChild":true},{"name":"Coin","pos":{"x":-2.559999942779541,"y":1.5,"z":-1.7200000286102296},"rot":{"x":0.0,"y":0.0,"z":0.0},"fullRotationData":[],"timelineAnimation":[],"bossSettings":[],"moveForward":[],"soData":[],"mat":[],"isChild":true},{"name":"Coin","pos":{"x":-5.760000228881836,"y":1.5,"z":-1.7200000286102296},"rot":{"x":0.0,"y":0.0,"z":0.0},"fullRotationData":[],"timelineAnimation":[],"bossSettings":[],"moveForward":[],"soData":[],"mat":[],"isChild":true},{"name":"largeBlock1","pos":{"x":-4.0,"y":-0.6000000238418579,"z":0.0},"rot":{"x":0.0,"y":0.0,"z":0.0},"fullRotationData":[],"timelineAnimation":[],"bossSettings":[],"moveForward":[],"soData":[],"mat":[],"isChild":true},{"name":"largeBlock1","pos":{"x":2.0,"y":-0.6000000238418579,"z":0.0},"rot":{"x":0.0,"y":0.0,"z":0.0},"fullRotationData":[],"timelineAnimation":[],"bossSettings":[],"moveForward":[],"soData":[],"mat":[],"isChild":true},{"name":"largeBlock1","pos":{"x":8.0,"y":-0.6000000238418579,"z":0.0},"rot":{"x":0.0,"y":0.0,"z":0.0},"fullRotationData":[],"timelineAnimation":[],"bossSettings":[],"moveForward":[],"soData":[],"mat":[],"isChild":true},{"name":"largeBlock1","pos":{"x":-10.0,"y":-0.6000000238418579,"z":0.0},"rot":{"x":0.0,"y":0.0,"z":0.0},"fullRotationData":[],"timelineAnimation":[],"bossSettings":[],"moveForward":[],"soData":[],"mat":[],"isChild":true},{"name":"largeBlock1","pos":{"x":-16.0,"y":-0.6000000238418579,"z":0.0},"rot":{"x":0.0,"y":0.0,"z":0.0},"fullRotationData":[],"timelineAnimation":[],"bossSettings":[],"moveForward":[],"soData":[],"mat":[],"isChild":true},{"name":"largeBlock1","pos":{"x":-22.0,"y":-0.6000000238418579,"z":0.0},"rot":{"x":0.0,"y":0.0,"z":0.0},"fullRotationData":[],"timelineAnimation":[],"bossSettings":[],"moveForward":[],"soData":[],"mat":[],"isChild":true},{"name":"largeBlock1","pos":{"x":14.0,"y":-0.6000000238418579,"z":0.0},"rot":{"x":0.0,"y":0.0,"z":0.0},"fullRotationData":[],"timelineAnimation":[],"bossSettings":[],"moveForward":[],"soData":[],"mat":[],"isChild":true},{"name":"Coin","pos":{"x":11.4399995803833,"y":1.5,"z":-0.11999999731779099},"rot":{"x":0.0,"y":0.0,"z":0.0},"fullRotationData":[],"timelineAnimation":[],"bossSettings":[],"moveForward":[],"soData":[],"mat":[],"isChild":true},{"name":"Coin","pos":{"x":13.039999961853028,"y":1.5,"z":-0.11999999731779099},"rot":{"x":0.0,"y":0.0,"z":0.0},"fullRotationData":[],"timelineAnimation":[],"bossSettings":[],"moveForward":[],"soData":[],"mat":[],"isChild":true},{"name":"Coin","pos":{"x":12.239999771118164,"y":1.5,"z":1.4800000190734864},"rot":{"x":0.0,"y":0.0,"z":0.0},"fullRotationData":[],"timelineAnimation":[],"bossSettings":[],"moveForward":[],"soData":[],"mat":[],"isChild":true},{"name":"Coin","pos":{"x":13.84000015258789,"y":1.5,"z":1.4800000190734864},"rot":{"x":0.0,"y":0.0,"z":0.0},"fullRotationData":[],"timelineAnimation":[],"bossSettings":[],"moveForward":[],"soData":[],"mat":[],"isChild":true},{"name":"Coin","pos":{"x":10.640000343322754,"y":1.5,"z":1.4800000190734864},"rot":{"x":0.0,"y":0.0,"z":0.0},"fullRotationData":[],"timelineAnimation":[],"bossSettings":[],"moveForward":[],"soData":[],"mat":[],"isChild":true},{"name":"Coin","pos":{"x":12.239999771118164,"y":1.5,"z":-1.7200000286102296},"rot":{"x":0.0,"y":0.0,"z":0.0},"fullRotationData":[],"timelineAnimation":[],"bossSettings":[],"moveForward":[],"soData":[],"mat":[],"isChild":true},{"name":"Coin","pos":{"x":13.84000015258789,"y":1.5,"z":-1.7200000286102296},"rot":{"x":0.0,"y":0.0,"z":0.0},"fullRotationData":[],"timelineAnimation":[],"bossSettings":[],"moveForward":[],"soData":[],"mat":[],"isChild":true},{"name":"Coin","pos":{"x":10.640000343322754,"y":1.5,"z":-1.7200000286102296},"rot":{"x":0.0,"y":0.0,"z":0.0},"fullRotationData":[],"timelineAnimation":[],"bossSettings":[],"moveForward":[],"soData":[],"mat":[],"isChild":true},{"name":"Coin","pos":{"x":-22.09000015258789,"y":1.5,"z":-0.11999999731779099},"rot":{"x":0.0,"y":0.0,"z":0.0},"fullRotationData":[],"timelineAnimation":[],"bossSettings":[],"moveForward":[],"soData":[],"mat":[],"isChild":true},{"name":"Coin","pos":{"x":-20.489999771118165,"y":1.5,"z":-0.11999999731779099},"rot":{"x":0.0,"y":0.0,"z":0.0},"fullRotationData":[],"timelineAnimation":[],"bossSettings":[],"moveForward":[],"soData":[],"mat":[],"isChild":true},{"name":"Coin","pos":{"x":-21.290000915527345,"y":1.5,"z":1.4800000190734864},"rot":{"x":0.0,"y":0.0,"z":0.0},"fullRotationData":[],"timelineAnimation":[],"bossSettings":[],"moveForward":[],"soData":[],"mat":[],"isChild":true},{"name":"Coin","pos":{"x":-19.690000534057618,"y":1.5,"z":1.4800000190734864},"rot":{"x":0.0,"y":0.0,"z":0.0},"fullRotationData":[],"timelineAnimation":[],"bossSettings":[],"moveForward":[],"soData":[],"mat":[],"isChild":true},{"name":"Coin","pos":{"x":-22.889999389648439,"y":1.5,"z":1.4800000190734864},"rot":{"x":0.0,"y":0.0,"z":0.0},"fullRotationData":[],"timelineAnimation":[],"bossSettings":[],"moveForward":[],"soData":[],"mat":[],"isChild":true},{"name":"Coin","pos":{"x":-21.290000915527345,"y":1.5,"z":-1.7200000286102296},"rot":{"x":0.0,"y":0.0,"z":0.0},"fullRotationData":[],"timelineAnimation":[],"bossSettings":[],"moveForward":[],"soData":[],"mat":[],"isChild":true},{"name":"Coin","pos":{"x":-19.690000534057618,"y":1.5,"z":-1.7200000286102296},"rot":{"x":0.0,"y":0.0,"z":0.0},"fullRotationData":[],"timelineAnimation":[],"bossSettings":[],"moveForward":[],"soData":[],"mat":[],"isChild":true},{"name":"Coin","pos":{"x":-22.889999389648439,"y":1.5,"z":-1.7200000286102296},"rot":{"x":0.0,"y":0.0,"z":0.0},"fullRotationData":[],"timelineAnimation":[],"bossSettings":[],"moveForward":[],"soData":[],"mat":[],"isChild":true},{"name":"palm","pos":{"x":3.140000104904175,"y":-0.25999999046325686,"z":0.0},"rot":{"x":0.0,"y":0.0,"z":0.0},"fullRotationData":[],"timelineAnimation":[],"bossSettings":[],"moveForward":[],"soData":[{"size":{"x":0.0,"y":0.0,"z":0.0},"bumperForce":0.0,"random_pos_x":2.0,"minPayers":0}],"mat":[],"isChild":true}]}